persistproc/__init__.py
persistproc/__main__.py
persistproc/cli.py
persistproc/client.py
persistproc/console.py
persistproc/log_manager.py
persistproc/logging_utils.py
persistproc/mcp_client_utils.py
persistproc/process_manager.py
persistproc/process_storage_manager.py
persistproc/process_types.py
persistproc/run.py
persistproc/serve.py
persistproc/shutdown.py
persistproc/text_formatters.py
persistproc/tools.py
persistproc-0.2.1.dist-info/METADATA
persistproc-0.2.1.dist-info/WHEEL
persistproc-0.2.1.dist-info/entry_points.txt
persistproc-0.2.1.dist-info/licenses/LICENSE
persistproc-0.2.1.dist-info/RECORD
