Metadata-Version: 2.4
Name: persistproc
Version: 0.2.1
Summary: A shared process layer for the modern, multi-agent development workflow.
Project-URL: Homepage, https://github.com/irskep/persistproc
Project-URL: Bug Tracker, https://github.com/irskep/persistproc/issues
Author-email: Steve Landey <steve@stevelandey.com>
License: MIT
License-File: LICENSE
Classifier: Development Status :: 4 - Beta
Classifier: Intended Audience :: Developers
Classifier: License :: OSI Approved :: MIT License
Classifier: Operating System :: MacOS
Classifier: Operating System :: POSIX
Classifier: Operating System :: Unix
Classifier: Programming Language :: Python :: 3
Classifier: Programming Language :: Python :: 3.10
Classifier: Programming Language :: Python :: 3.11
Classifier: Programming Language :: Python :: 3.12
Classifier: Programming Language :: Python :: 3.13
Classifier: Topic :: System :: Systems Administration
Classifier: Topic :: Utilities
Requires-Python: >=3.10
Requires-Dist: fastmcp==2.9.2
Requires-Dist: rich>=14.0.0
Provides-Extra: dev
Requires-Dist: pre-commit>=3.0.0; extra == 'dev'
Requires-Dist: pytest-asyncio>=0.21; extra == 'dev'
Requires-Dist: pytest-cov>=4.0; extra == 'dev'
Requires-Dist: pytest-timeout>=2.1.0; extra == 'dev'
Requires-Dist: pytest-xdist; extra == 'dev'
Requires-Dist: pytest>=7.0; extra == 'dev'
Requires-Dist: ruff; extra == 'dev'
Requires-Dist: uvicorn>=0.35.0; extra == 'dev'
Provides-Extra: docs
Requires-Dist: coverage-badge; extra == 'docs'
Requires-Dist: mkdocs-github-admonitions-plugin; extra == 'docs'
Requires-Dist: mkdocs-material>=9.4.6; extra == 'docs'
Requires-Dist: mkdocs-mermaid2-plugin>=1.1.1; extra == 'docs'
Requires-Dist: mkdocs>=1.5.3; extra == 'docs'
Requires-Dist: mkdocstrings[python]>=0.23.0; extra == 'docs'
Requires-Dist: pymdown-extensions>=10.3.1; extra == 'docs'
